llmask/__init__.py
llmask/cli.py
llmask/model.py
llmask/transform.py
llmask-1.1.0.dist-info/LICENSE
llmask-1.1.0.dist-info/METADATA
llmask-1.1.0.dist-info/WHEEL
llmask-1.1.0.dist-info/entry_points.txt
llmask-1.1.0.dist-info/RECORD
